{
  "id": "mv-2022-hyakkiyagyo",
  "title": "百機夜行 - 咲葉良",
  "category": "MV",
  "description": [
    "Music video for Saya Ryou’s debut track “百機夜行,” crafted as a cinematic collaboration with director Rimi Watanabe.",
    "",
    "女優・アイドルとして活動してきた咲葉良の歌手デビュー曲「百機夜行」のMVを制作。",
    "フォトグラファー／VJ／映像作家として活躍するRimi WatanageがDirectorを務め、シネマティックな世界観で構築しました。"
  ],
  "year": 2022,
  "tags": [
    "UnrealEngine"
  ],
  "thumbnail": "assets/images/mv_2022_hyakkiyagyo.webp",
  "videoUrl": "https://www.youtube.com/watch?v=NMc487BZRWM",
  "images": []
}

